dmddl/__init__.py
dmddl/cli.py
dmddl/config/__init__.py
dmddl/config/proxy.py
dmddl/config/settings.py
dmddl/models/__init__.py
dmddl/models/llm.py
dmddl/models/prompt.py
dmddl-0.2.26.dist-info/entry_points.txt
dmddl-0.2.26.dist-info/LICENSE
dmddl-0.2.26.dist-info/METADATA
dmddl-0.2.26.dist-info/WHEEL
dmddl-0.2.26.dist-info/RECORD
