Metadata-Version: 2.3
Name: dmddl
Version: 0.2.26
Summary: cli tool for creating insert script from ddl script
License: MIT
Author: HoJLter
Author-email: hojlter.work@gmail.com
Requires-Python: >=3.13
Classifier: License :: OSI Approved :: MIT License
Classifier: Programming Language :: Python :: 3
Classifier: Programming Language :: Python :: 3.13
Requires-Dist: aiohttp (>=3.11.18,<4.0.0)
Requires-Dist: bs4 (>=0.0.2,<0.0.3)
Requires-Dist: dotenv (>=0.9.9,<0.10.0)
Requires-Dist: questionary (>=2.1.0,<3.0.0)
Requires-Dist: requests (>=2.32.3,<3.0.0)
Requires-Dist: rich (>=14.0.0,<15.0.0)
